imio.prettylink-1.24-py3.12-nspkg.pth
imio/prettylink/__init__.py
imio/prettylink/adapters.py
imio/prettylink/configure.zcml
imio/prettylink/interfaces.py
imio/prettylink/testing.py
imio/prettylink/testing.zcml
imio/prettylink/locales/imio.prettylink.pot
imio/prettylink/locales/sync_pos.sh
imio/prettylink/locales/en/LC_MESSAGES/imio.prettylink.po
imio/prettylink/locales/fr/LC_MESSAGES/imio.prettylink.po
imio/prettylink/tests/__init__.py
imio/prettylink/tests/test_adapter.py
imio_prettylink-1.24.dist-info/METADATA
imio_prettylink-1.24.dist-info/WHEEL
imio_prettylink-1.24.dist-info/entry_points.txt
imio_prettylink-1.24.dist-info/namespace_packages.txt
imio_prettylink-1.24.dist-info/top_level.txt
imio_prettylink-1.24.dist-info/RECORD
