Metadata-Version: 2.4
Name: imio.prettylink
Version: 1.24
Summary: Manage generation of a pretty link to an element including coloration, leading icons, ...
Home-page: http://pypi.python.org/pypi/imio.prettylink
Author: Gauthier Bastien
Author-email: gauthier.bastien@imio.be
License: GPL
Keywords: plone pretty link utils dev imio
Classifier: Environment :: Web Environment
Classifier: Framework :: Plone
Classifier: Framework :: Plone :: 4.3
Classifier: Framework :: Plone :: 5.2
Classifier: Framework :: Plone :: 6.0
Classifier: Framework :: Plone :: 6.1
Classifier: Programming Language :: Python
Classifier: Programming Language :: Python :: 2.7
Classifier: Programming Language :: Python :: 3.8
Classifier: Programming Language :: Python :: 3.9
Classifier: Programming Language :: Python :: 3.10
Classifier: Programming Language :: Python :: 3.11
Classifier: Programming Language :: Python :: 3.12
Classifier: Programming Language :: Python :: 3.13
Requires-Dist: plone.api
Requires-Dist: imio.helpers>=0.52
Requires-Dist: setuptools
Provides-Extra: test
Requires-Dist: plone.app.testing; extra == "test"
Requires-Dist: plone.app.robotframework; extra == "test"
Dynamic: author
Dynamic: author-email
Dynamic: classifier
Dynamic: description
Dynamic: home-page
Dynamic: keywords
Dynamic: license
Dynamic: provides-extra
Dynamic: requires-dist
Dynamic: summary
